zelthy/__init__.py
zelthy/api/__init__.py
zelthy/api/app_auth/__init__.py
zelthy/api/app_auth/urls.py
zelthy/api/app_auth/profile/__init__.py
zelthy/api/app_auth/profile/v1/__init__.py
zelthy/api/app_auth/profile/v1/serializers.py
zelthy/api/app_auth/profile/v1/urls.py
zelthy/api/app_auth/profile/v1/utils.py
zelthy/api/app_auth/profile/v1/views.py
zelthy/api/platform/__init__.py
zelthy/api/platform/urls.py
zelthy/api/platform/auth/__init__.py
zelthy/api/platform/auth/v1/__init__.py
zelthy/api/platform/auth/v1/serializers.py
zelthy/api/platform/auth/v1/urls.py
zelthy/api/platform/auth/v1/views.py
zelthy/api/platform/codeassist/__init__.py
zelthy/api/platform/codeassist/v1/__init__.py
zelthy/api/platform/codeassist/v1/urls.py
zelthy/api/platform/codeassist/v1/utils.py
zelthy/api/platform/codeassist/v1/views.py
zelthy/api/platform/packages/__init__.py
zelthy/api/platform/packages/v1/__init__.py
zelthy/api/platform/packages/v1/urls.py
zelthy/api/platform/packages/v1/views.py
zelthy/api/platform/permissions/__init__.py
zelthy/api/platform/permissions/v1/__init__.py
zelthy/api/platform/permissions/v1/serializers.py
zelthy/api/platform/permissions/v1/urls.py
zelthy/api/platform/permissions/v1/views.py
zelthy/api/platform/tasks/__init__.py
zelthy/api/platform/tasks/v1/__init__.py
zelthy/api/platform/tasks/v1/serializers.py
zelthy/api/platform/tasks/v1/urls.py
zelthy/api/platform/tasks/v1/views.py
zelthy/api/platform/tenancy/__init__.py
zelthy/api/platform/tenancy/v1/__init__.py
zelthy/api/platform/tenancy/v1/serializers.py
zelthy/api/platform/tenancy/v1/urls.py
zelthy/api/platform/tenancy/v1/views.py
zelthy/apps/__init__.py
zelthy/apps/appauth/__init__.py
zelthy/apps/appauth/admin.py
zelthy/apps/appauth/apps.py
zelthy/apps/appauth/auth_backend.py
zelthy/apps/appauth/models.py
zelthy/apps/appauth/serializers.py
zelthy/apps/appauth/signals.py
zelthy/apps/appauth/tests.py
zelthy/apps/appauth/urls.py
zelthy/apps/appauth/views.py
zelthy/apps/appauth/migrations/0001_initial.py
zelthy3-0.1.2.dist-info/LICENSE
zelthy3-0.1.2.dist-info/METADATA
zelthy3-0.1.2.dist-info/WHEEL
zelthy3-0.1.2.dist-info/entry_points.txt
zelthy3-0.1.2.dist-info/top_level.txt
zelthy3-0.1.2.dist-info/RECORD
