Metadata-Version: 2.1
Name: zelthy3
Version: 0.1.2
Summary: Zelthy3: multi-tenant Django framework for building business apps
Home-page: https://github.com/Healthlane-Technologies/zelthy3
Author: Zelthy ("Healthlane Technologies")
Author-email: maintainers@zelthy.com
License: Apache License 2.0
Classifier: Framework :: Django
Classifier: Programming Language :: Python
License-File: LICENSE
Requires-Dist: django >=3.0
Requires-Dist: psycopg2-binary
Requires-Dist: django-tenants
Requires-Dist: djangorestframework
Requires-Dist: django-rest-knox
Requires-Dist: celery ==5.3.1
Requires-Dist: flake8 ==6.1.0
Requires-Dist: django-cors-headers ==4.2.0
Requires-Dist: pluginbase ==1.0.1
Requires-Dist: click ==8.1.7
Requires-Dist: phonenumberslite ==8.13.23
Requires-Dist: django-phonenumber-field ==7.1.0
Requires-Dist: django-redis ==5.3.0
Requires-Dist: django-cachalot ==2.6.1
Requires-Dist: django-debug-toolbar ==4.2.0
Requires-Dist: django-formtools ==2.4.1
Requires-Dist: django-crispy-forms ==2.0
Requires-Dist: crispy-bootstrap5 ==0.7
Requires-Dist: cookiecutter ==2.3.0
Requires-Dist: boto3 ==1.28.52
Requires-Dist: botocore ==1.31.52
Requires-Dist: django-storages ==1.14
Requires-Dist: django-celery-beat ==2.5.0
Requires-Dist: django-smtp-ssl ==1.0
Requires-Dist: PyJWT ==2.8.0
Requires-Dist: XlsxWriter ==3.1.9
Requires-Dist: pydub ==0.25.1
Requires-Dist: django-celery-results ==2.5.1
Requires-Dist: django-environ ==0.11.2
Requires-Dist: pytz ==2024.1
